{
  "questions": [
    {
      "id": 1,
      "question": "Quel est le poids moyen du cerveau humain adulte?",
      "choices": [
        "Environ 1,4 kilogrammes",
        "Environ 1,0 kilogrammes",
        "Environ 2,0 kilogrammes",
        "Environ 0,5 kilogrammes"
      ],
      "answer": "Environ 1,4 kilogrammes"
    },
    {
      "id": 2,
      "question": "Quel est le principal rôle du cerveau dans le corps humain?",
      "choices": [
        "Produire des hormones",
        "Contrôler et réguler les fonctions corporelles et les activités mentales",
        "Digérer les aliments",
        "Filtrer le sang"
      ],
      "answer": "Contrôler et réguler les fonctions corporelles et les activités mentales"
    },
    {
      "id": 3,
      "question": "Combien de neurones y a-t-il approximativement dans un cerveau humain?",
      "choices": [
        "Environ 100 millions",
        "Environ 1 milliard",
        "Environ 86 milliards",
        "Environ 1 trillion"
      ],
      "answer": "Environ 86 milliards"
    },
    {
      "id": 4,
      "question": "Quelle partie du cerveau est principalement responsable de la mémoire?",
      "choices": [
        "Le cervelet",
        "Le cortex cérébral",
        "L'hippocampe",
        "Le tronc cérébral"
      ],
      "answer": "L'hippocampe"
    },
    {
      "id": 5,
      "question": "Quel est le nom de la barrière qui protège le cerveau des substances nocives dans le sang?",
      "choices": [
        "La barrière hémato-encéphalique",
        "La barrière méningée",
        "La barrière neurale",
        "La barrière sanguine"
      ],
      "answer": "La barrière hémato-encéphalique"
    },
    {
      "id": 6,
      "question": "Quelle région du cerveau est impliquée dans la régulation des émotions?",
      "choices": [
        "Le cortex préfrontal",
        "Le tronc cérébral",
        "Le système limbique",
        "Le cervelet"
      ],
      "answer": "Le système limbique"
    },
    {
      "id": 7,
      "question": "Quel neurotransmetteur est principalement associé au plaisir et à la récompense?",
      "choices": [
        "La sérotonine",
        "La dopamine",
        "L'adrénaline",
        "Le glutamate"
      ],
      "answer": "La dopamine"
    },
    {
      "id": 8,
      "question": "Quel est le terme utilisé pour décrire la capacité du cerveau à se réorganiser et à former de nouvelles connexions neuronales tout au long de la vie?",
      "choices": [
        "La neurogenèse",
        "La neuroplasticité",
        "La neuromodulation",
        "La neurodiversité"
      ],
      "answer": "La neuroplasticité"
    },
    {
      "id": 9,
      "question": "Quelle glande, située dans le cerveau, est souvent appelée le \"maître régulateur\" en raison de son rôle central dans la régulation des autres glandes endocrines?",
      "choices": [
        "La glande pinéale",
        "L'hypophyse (ou glande pituitaire)",
        "La thyroïde",
        "Les glandes surrénales"
      ],
      "answer": "L'hypophyse (ou glande pituitaire)"
    },
    {
      "id": 10,
      "question": "Quel scientifique est connu pour ses travaux sur le cerveau et pour avoir proposé la théorie de la localisation des fonctions cérébrales spécifiques?",
      "choices": [
        "Sigmund Freud",
        "Carl Jung",
        "Paul Broca",
        "Ivan Pavlov"
      ],
      "answer": "Paul Broca"
    }
  ]
}
